led_kurokku/__init__.py
led_kurokku/cli_main.py
led_kurokku/core.py
led_kurokku/main.py
led_kurokku/models.py
led_kurokku/web_server.py
led_kurokku/cli/__init__.py
led_kurokku/cli/commands/__init__.py
led_kurokku/cli/commands/alert.py
led_kurokku/cli/commands/config.py
led_kurokku/cli/commands/instances.py
led_kurokku/cli/commands/template.py
led_kurokku/cli/commands/weather.py
led_kurokku/cli/models/__init__.py
led_kurokku/cli/models/instance.py
led_kurokku/cli/models/weather.py
led_kurokku/cli/services/__init__.py
led_kurokku/cli/services/weather_service.py
led_kurokku/cli/utils/__init__.py
led_kurokku/cli/utils/config_helpers.py
led_kurokku/cli/utils/redis_helpers.py
led_kurokku/cli/utils/weather_api.py
led_kurokku/tm1637/__init__.py
led_kurokku/tm1637/base_driver.py
led_kurokku/tm1637/console.py
led_kurokku/tm1637/factory.py
led_kurokku/tm1637/led.py
led_kurokku/tm1637/virtual.py
led_kurokku/tm1637/websocket.py
led_kurokku/utils/__init__.py
led_kurokku/utils/logging.py
led_kurokku/web/static/README.md
led_kurokku/web/templates/web_kurokku/index.html
led_kurokku/widgets/__init__.py
led_kurokku/widgets/alert.py
led_kurokku/widgets/animation.py
led_kurokku/widgets/base.py
led_kurokku/widgets/clock.py
led_kurokku/widgets/factory.py
led_kurokku/widgets/message.py
led_kurokku-0.3.1.dist-info/METADATA
led_kurokku-0.3.1.dist-info/WHEEL
led_kurokku-0.3.1.dist-info/entry_points.txt
led_kurokku-0.3.1.dist-info/licenses/LICENSE
led_kurokku-0.3.1.dist-info/RECORD
