Metadata-Version: 2.4
Name: led-kurokku
Version: 0.3.1
Author-email: swilcox <steven@wilcoxzone.com>
License-File: LICENSE
Requires-Python: >=3.11
Requires-Dist: aiohttp>=3.8.5
Requires-Dist: click>=8.1.8
Requires-Dist: loguru>=0.7.3
Requires-Dist: pycron>=3.2.0
Requires-Dist: pydantic>=2.11.3
Requires-Dist: pyyaml>=6.0.1
Requires-Dist: redis>=5.2.1
Provides-Extra: rpi
Requires-Dist: rpi-gpio>=0.7.1; extra == 'rpi'
